[
  {
    "id": 1,
    "title": "노 드라우트 115g",
    "price": 32000,
    "price2": "32,000",
    "rate": 4.57,
    "quantity": 1,
    "itemtotal": 32000,
    "category": "샴푸",
    "img": "./images/hair/53542662155864380_558785816.jpg",
    "incense": "옥수수 라임 자몽",
    "desc": "자몽과 라임 오일이 듬뿍 담긴 파우더가 물로 샴푸 한듯한 상쾌함을 선사합니다."
  },
  {
    "id": 2,
    "title": "노 드라우트 50g",
    "price": 17000,
    "price2": "17,000",
    "rate": 4.71,
    "quantity": 1,
    "itemtotal": 17000,
    "category": "샴푸",
    "img": "./images/hair/46310072421119450_916126351.jpg",
    "incense": "옥수수 라임 자몽",
    "desc": "자몽과 라임 오일이 듬뿍 담긴 파우더가 물로 샴푸 한듯한 상쾌함을 선사합니다."
  },
  {
    "id": 3,
    "title": "대디-오 1000g",
    "price": 120000,
    "price2": "120,000",
    "rate": 4.94,
    "quantity": 1,
    "itemtotal": 120000,
    "category": "샴푸",
    "img": "./images/hair/18839156387712568_1212410731.jpg",
    "incense": "바이올렛 리프 애브솔루트, 로즈 애브솔루트, 베르가못 오일",
    "desc": "파우더리한 캔디 바이올렛 향기에 상큼한 베르가못과 장미가 어우러져 우아하면서도 달콤한 플로럴 향을 선사합니다."
  },
  {
    "id": 4,
    "title": "대디-오 100g",
    "price": 22000,
    "price2": "22,000",
    "rate": 4.7,
    "quantity": 1,
    "itemtotal": 22000,
    "category": "샴푸",
    "img": "./images/hair/95197763436846189_1042174738.jpg",
    "incense": "바이올렛 리프 애브솔루트, 로즈 애브솔루트, 베르가못 오일",
    "desc": "파우더리한 캔디 바이올렛 향기에 상큼한 베르가못과 장미가 어우러져 우아하면서도 달콤한 플로럴 향을 선사합니다."
  },
  {
    "id": 5,
    "title": "대디-오 250g",
    "price": 44000,
    "price2": "44,000",
    "rate": 4.8,
    "quantity": 1,
    "itemtotal": 44000,
    "category": "샴푸",
    "img": "./images/hair/95197803392264354_1417493172.jpg",
    "incense": "바이올렛 리프 애브솔루트, 로즈 애브솔루트, 베르가못 오일",
    "desc": "파우더리한 캔디 바이올렛 향기에 상큼한 베르가못과 장미가 어우러져 우아하면서도 달콤한 플로럴 향을 선사합니다."
  },
  {
    "id": 6,
    "title": "대디-오 500g",
    "price": 73000,
    "price2": "73,000",
    "rate": 4.83,
    "quantity": 1,
    "itemtotal": 73000,
    "category": "샴푸",
    "img": "./images/hair/82612307248503130_2093785994.jpg",
    "incense": "바이올렛 리프 애브솔루트, 로즈 애브솔루트, 베르가못 오일",
    "desc": "파우더리한 캔디 바이올렛 향기에 상큼한 베르가못과 장미가 어우러져 우아하면서도 달콤한 플로럴 향을 선사합니다."
  },
  {
    "id": 7,
    "title": "두부 200g",
    "price": 50000,
    "price2": "50,000",
    "rate": 4.8,
    "quantity": 1,
    "itemtotal": 50000,
    "category": "샴푸",
    "img": "./images/hair/6509668426286956_1857594826.jpg",
    "incense": "두부 올리브",
    "desc": "모발도 휴식이 필요해요, 부드러운 두부로 상처받은 모발의 건강을 되찾아 주세요!"
  },
  {
    "id": 8,
    "title": "두부 400g",
    "price": 80000,
    "price2": "80,000",
    "rate": 4.83,
    "quantity": 1,
    "itemtotal": 80000,
    "category": "샴푸",
    "img": "./images/hair/82634928274673390_430446694.jpg",
    "incense": "두부 올리브",
    "desc": "모발도 휴식이 필요해요, 부드러운 두부로 상처받은 모발의 건강을 되찾아 주세요!"
  },
  {
    "id": 9,
    "title": "두부 90g",
    "price": 26000,
    "price2": "26,000",
    "rate": 4.29,
    "quantity": 1,
    "itemtotal": 26000,
    "category": "샴푸",
    "img": "./images/hair/31544032274323048_384526178.jpg",
    "incense": "두부 올리브",
    "desc": "모발도 휴식이 필요해요, 부드러운 두부로 상처받은 모발의 건강을 되찾아 주세요!"
  },
  {
    "id": 10,
    "title": "리햅 1000g",
    "price": 120000,
    "price2": "120,000",
    "rate": 4.89,
    "quantity": 1,
    "itemtotal": 120000,
    "category": "샴푸",
    "img": "./images/hair/42328380316450299_480975858.jpg",
    "incense": "망고 로즈마리 호호바오일 페퍼민트",
    "desc": "신선한 파파야, 파인애플, 키위 그리고 망고 주스를 직접 짜내고, 엑스트라 버진 오일과 호호바 오일을 더해 모발을 튼튼하게 가꾸어주는 샴푸를 만들었습니다."
  },
  {
    "id": 11,
    "title": "리햅 100g",
    "price": 22000,
    "price2": "22,000",
    "rate": 4.58,
    "quantity": 1,
    "itemtotal": 22000,
    "category": "샴푸",
    "img": "./images/hair/20469305052070269_1055608952.jpg",
    "incense": "망고 로즈마리 호호바오일 페퍼민트",
    "desc": "신선한 파파야, 파인애플, 키위 그리고 망고 주스를 직접 짜내고, 엑스트라 버진 오일과 호호바 오일을 더해 모발을 튼튼하게 가꾸어주는 샴푸를 만들었습니다."
  },
  {
    "id": 12,
    "title": "리햅 250g",
    "price": 44000,
    "price2": "44,000",
    "rate": 4.78,
    "quantity": 1,
    "itemtotal": 44000,
    "category": "샴푸",
    "img": "./images/hair/79478747452277_1600186326.jpg",
    "incense": "망고 로즈마리 호호바오일 페퍼민트",
    "desc": "신선한 파파야, 파인애플, 키위 그리고 망고 주스를 직접 짜내고, 엑스트라 버진 오일과 호호바 오일을 더해 모발을 튼튼하게 가꾸어주는 샴푸를 만들었습니다."
  },
  {
    "id": 13,
    "title": "리햅 500g",
    "price": 73000,
    "price2": "73,000",
    "rate": 4.83,
    "quantity": 1,
    "itemtotal": 73000,
    "category": "샴푸",
    "img": "./images/hair/11480374525017967_1793668318.jpg",
    "incense": "망고 로즈마리 호호바오일 페퍼민트",
    "desc": "신선한 파파야, 파인애플, 키위 그리고 망고 주스를 직접 짜내고, 엑스트라 버진 오일과 호호바 오일을 더해 모발을 튼튼하게 가꾸어주는 샴푸를 만들었습니다."
  },
  {
    "id": 14,
    "title": "리햅 솔티 600g",
    "price": 75000,
    "price2": "75,000",
    "rate": 4.86,
    "quantity": 1,
    "itemtotal": 75000,
    "category": "샴푸",
    "img": "./images/hair/1508661881013657_55215309.jpg",
    "incense": "망고 로즈마리 호호바오일 페퍼민트",
    "desc": "신선한 파파야, 파인애플, 키위 그리고 망고 주스를 직접 짜내고, 엑스트라 버진 오일과 호호바 오일을 더해 모발을 튼튼하게 가꾸어주는 샴푸를 만들었습니다."
  },
  {
    "id": 15,
    "title": "망고 코-워시 100g",
    "price": 25000,
    "price2": "25,000",
    "rate": 5.0,
    "quantity": 1,
    "itemtotal": 25000,
    "category": "샴푸",
    "img": "./images/hair/43392402277368160_725262169.jpg",
    "incense": "망고 오렌지",
    "desc": "오렌지와 타임의 달콤한 향기는 따스한 여름날 해안가에 내리쬐는 햇볕을 닮았어요."
  },
  {
    "id": 16,
    "title": "바나나 290g",
    "price": 44000,
    "price2": "44,000",
    "rate": 4.75,
    "quantity": 1,
    "itemtotal": 44000,
    "category": "샴푸",
    "img": "./images/hair/52675699203962583_368512084.jpg",
    "incense": "통카 바닐라 바다소금",
    "desc": "부드러운 바나나는 달콤한 향기뿐 아니라, 언제 어디서나 눈부시게 윤기 나는 모발을 지켜주죠."
  },
  {
    "id": 17,
    "title": "빅 130g",
    "price": 22000,
    "price2": "22,000",
    "rate": 4.89,
    "quantity": 1,
    "itemtotal": 22000,
    "category": "샴푸",
    "img": "./images/hair/82635073647606662_1027786323.jpg",
    "incense": "시칠리안 만다린 오일, 네롤리 오일, 오렌지 플라워 애브솔루트, 바닐라 애브솔루트",
    "desc": "여름 해변을 연상시키는 밝은 시트러스와 네롤리 플로럴의 부드러운 조합 위에, 따뜻한 바닐라의 달콤함이 감돌아 상쾌하면서도 포근한 향입니다."
  },
  {
    "id": 18,
    "title": "빅 330g",
    "price": 44000,
    "price2": "44,000",
    "rate": 4.84,
    "quantity": 1,
    "itemtotal": 44000,
    "category": "샴푸",
    "img": "./images/hair/8098872272202657_1074327500.jpg",
    "incense": "시칠리안 만다린 오일, 네롤리 오일, 오렌지 플라워 애브솔루트, 바닐라 애브솔루트",
    "desc": "여름 해변을 연상시키는 밝은 시트러스와 네롤리 플로럴의 부드러운 조합 위에, 따뜻한 바닐라의 달콤함이 감돌아 상쾌하면서도 포근한 향입니다."
  },
  {
    "id": 19,
    "title": "빅 640g",
    "price": 75000,
    "price2": "75,000",
    "rate": 4.89,
    "quantity": 1,
    "itemtotal": 75000,
    "category": "샴푸",
    "img": "./images/hair/82635101509166855_1791767482.jpg",
    "incense": "시칠리안 만다린 오일, 네롤리 오일, 오렌지 플라워 애브솔루트, 바닐라 애브솔루트",
    "desc": "여름 해변을 연상시키는 밝은 시트러스와 네롤리 플로럴의 부드러운 조합 위에, 따뜻한 바닐라의 달콤함이 감돌아 상쾌하면서도 포근한 향입니다."
  },
  {
    "id": 20,
    "title": "스퀵 125g",
    "price": 22000,
    "price2": "22,000",
    "rate": 4.71,
    "quantity": 1,
    "itemtotal": 22000,
    "category": "샴푸",
    "img": "./images/hair/aa.jpg",
    "incense": "아이리쉬모스 키위 파인애플 바닷소금",
    "desc": "뽀득뽀득 깨끗하게 빛나는 모발의 비결!"
  },
  {
    "id": 21,
    "title": "스퀵 280g",
    "price": 44000,
    "price2": "44,000",
    "rate": 4.87,
    "quantity": 1,
    "itemtotal": 44000,
    "category": "샴푸",
    "img": "./images/hair/aa.jpg",
    "incense": "아이리쉬모스 키위 파인애플 바닷소금",
    "desc": "뽀득뽀득 깨끗하게 빛나는 모발의 비결!"
  },
  {
    "id": 22,
    "title": "스퀵 575g",
    "price": 75000,
    "price2": "75,000",
    "rate": 4.8,
    "quantity": 1,
    "itemtotal": 75000,
    "category": "샴푸",
    "img": "./images/hair/aa.jpg",
    "incense": "아이리쉬모스 키위 파인애플 바닷소금",
    "desc": "뽀득뽀득 깨끗하게 빛나는 모발의 비결!"
  },
  {
    "id": 23,
    "title": "와사비 샨 쿠이 1100g",
    "price": 143000,
    "price2": "143,000",
    "rate": 4.97,
    "quantity": 1,
    "itemtotal": 143000,
    "category": "샴푸",
    "img": "./images/hair/46299117836312510_855473277.jpg",
    "incense": "장미 바다소금 레몬",
    "desc": "강렬하고 시원한 거품으로 두피에 슈퍼 파워를 불어 넣어주세요. 당신은 나의 히어로!"
  },
  {
    "id": 24,
    "title": "와사비 샨 쿠이 110g",
    "price": 26000,
    "price2": "26,000",
    "rate": 4.66,
    "quantity": 1,
    "itemtotal": 26000,
    "category": "샴푸",
    "img": "./images/hair/11480633350483023_1214439074.jpg",
    "incense": "장미 바다소금 레몬",
    "desc": "강렬하고 시원한 거품으로 두피에 슈퍼 파워를 불어 넣어주세요. 당신은 나의 히어로!"
  },
  {
    "id": 25,
    "title": "와사비 샨 쿠이 300g",
    "price": 58000,
    "price2": "58,000",
    "rate": 4.76,
    "quantity": 1,
    "itemtotal": 58000,
    "category": "샴푸",
    "img": "./images/hair/82635077383414166_929358403.jpg",
    "incense": "장미 바다소금 레몬",
    "desc": "강렬하고 시원한 거품으로 두피에 슈퍼 파워를 불어 넣어주세요. 당신은 나의 히어로!"
  },
  {
    "id": 26,
    "title": "와사비 샨 쿠이 600g",
    "price": 90000,
    "price2": "90,000",
    "rate": 4.88,
    "quantity": 1,
    "itemtotal": 90000,
    "category": "샴푸",
    "img": "./images/hair/8098769944795159_7477659.jpg",
    "incense": "장미 바다소금 레몬",
    "desc": "강렬하고 시원한 거품으로 두피에 슈퍼 파워를 불어 넣어주세요. 당신은 나의 히어로!"
  },
  {
    "id": 27,
    "title": "진저 275g",
    "price": 56000,
    "price2": "56,000",
    "rate": 4.6,
    "quantity": 1,
    "itemtotal": 56000,
    "category": "샴푸",
    "img": "./images/hair/21177908094411873_630438258.jpg",
    "incense": "생강 로즈마리 아보카도 바닷소금",
    "desc": "톡 쏘는 생강 뿌리가 두피를 구석구석 말끔하게 씻겨주면, 신선한 허브가 상쾌한 마무리를 완성해 줄 거예요."
  },
  {
    "id": 28,
    "title": "페얼리 트레이디드 허니 1100g",
    "price": 143000,
    "price2": "143,000",
    "rate": 5.0,
    "quantity": 1,
    "itemtotal": 143000,
    "category": "샴푸",
    "img": "./images/hair/10871208801835115_1314652697.jpg",
    "incense": "아마씨 꿀",
    "desc": "잠비아에서 채취하고 공정무역을 거친 꿀을 샴푸병에 절반 이상 담아 모발을 더욱 촉촉하고 윤기나게 가꾸어줍니다."
  },
  {
    "id": 29,
    "title": "페얼리 트레이디드 허니 110g",
    "price": 26000,
    "price2": "26,000",
    "rate": 4.64,
    "quantity": 1,
    "itemtotal": 26000,
    "category": "샴푸",
    "img": "./images/hair/65094394626678090_1280647990.jpg",
    "incense": "아마씨 꿀",
    "desc": "잠비아에서 채취하고 공정무역을 거친 꿀을 샴푸병에 절반 이상 담아 모발을 더욱 촉촉하고 윤기나게 가꾸어줍니다."
  },
  {
    "id": 30,
    "title": "페얼리 트레이디드 허니 300g",
    "price": 56000,
    "price2": "56,000",
    "rate": 4.76,
    "quantity": 1,
    "itemtotal": 56000,
    "category": "샴푸",
    "img": "./images/hair/80349549540495082_1916992064.jpg",
    "incense": "아마씨 꿀",
    "desc": "잠비아에서 채취하고 공정무역을 거친 꿀을 샴푸병에 절반 이상 담아 모발을 더욱 촉촉하고 윤기나게 가꾸어줍니다."
  },
  {
    "id": 31,
    "title": "페얼리 트레이디드 허니 600g",
    "price": 90000,
    "price2": "90,000",
    "rate": 4.74,
    "quantity": 1,
    "itemtotal": 90000,
    "category": "샴푸",
    "img": "./images/hair/77680113807470328_1221701907.jpg",
    "incense": "아마씨 꿀",
    "desc": "잠비아에서 채취하고 공정무역을 거친 꿀을 샴푸병에 절반 이상 담아 모발을 더욱 촉촉하고 윤기나게 가꾸어줍니다."
  },
  {
    "id": 32,
    "title": "고디바 55g",
    "price": 20000,
    "price2": "20,000",
    "rate": 4.0,
    "quantity": 1,
    "itemtotal": 20000,
    "category": "샴푸 바",
    "img": "./images/shampoobar/01.jpg",
    "incense": "",
    "desc": ""
  },
  {
    "id": 33,
    "title": "뉴 55g",
    "price": 20000,
    "price2": "20,000",
    "rate": 4.8,
    "quantity": 1,
    "itemtotal": 20000,
    "category": "샴푸 바",
    "img": "./images/shampoobar/02.jpg",
    "incense": "",
    "desc": ""
  },
  {
    "id": 34,
    "title": "망고 코-워시 100g",
    "price": 25000,
    "price2": "25,000",
    "rate": 5.0,
    "quantity": 1,
    "itemtotal": 25000,
    "category": "샴푸 바",
    "img": "./images/shampoobar/03.jpg",
    "incense": "",
    "desc": ""
  },
  {
    "id": 35,
    "title": "몬탈바노 55g",
    "price": 20000,
    "price2": "20,000",
    "rate": 5.0,
    "quantity": 1,
    "itemtotal": 20000,
    "category": "샴푸 바",
    "img": "./images/shampoobar/04.jpg",
    "incense": "",
    "desc": ""
  },
  {
    "id": 36,
    "title": "바나나 코-워시 100g",
    "price": 25000,
    "price2": "25,000",
    "rate": 5.0,
    "quantity": 1,
    "itemtotal": 25000,
    "category": "샴푸 바",
    "img": "./images/shampoobar/05.jpg",
    "incense": "",
    "desc": ""
  },
  {
    "id": 37,
    "title": "씨닉 55g",
    "price": 20000,
    "price2": "20,000",
    "rate": 5.0,
    "quantity": 1,
    "itemtotal": 20000,
    "category": "샴푸 바",
    "img": "./images/shampoobar/06.jpg",
    "incense": "",
    "desc": ""
  },
  {
    "id": 38,
    "title": "점핑 주니퍼 55g",
    "price": 20000,
    "price2": "20,000",
    "rate": 5.0,
    "quantity": 1,
    "itemtotal": 20000,
    "category": "샴푸 바",
    "img": "./images/shampoobar/07.jpg",
    "incense": "",
    "desc": ""
  },
  {
    "id": 39,
    "title": "제이슨 앤 더 아르간 오일 55g",
    "price": 20000,
    "price2": "20,000",
    "rate": 4.6,
    "quantity": 1,
    "itemtotal": 20000,
    "category": "샴푸 바",
    "img": "./images/shampoobar/08.jpg",
    "incense": "",
    "desc": ""
  },
  {
    "id": 40,
    "title": "코코넛 라이스 케이크 55g",
    "price": 20000,
    "price2": "20,000",
    "rate": 5.0,
    "quantity": 1,
    "itemtotal": 20000,
    "category": "샴푸 바",
    "img": "./images/shampoobar/09.jpg",
    "incense": "",
    "desc": ""
  },
  {
    "id": 41,
    "title": "허니 아이 워시드 마이 헤어 55g",
    "price": 20000,
    "price2": "20,000",
    "rate": 4.6,
    "quantity": 1,
    "itemtotal": 20000,
    "category": "샴푸 바",
    "img": "./images/shampoobar/10.jpg",
    "incense": "",
    "desc": ""
  },
  {
    "id": 42,
    "title": "아보카도 코-워시 100g",
    "price": 25000,
    "price2": "25,000",
    "rate": 0.0,
    "quantity": 1,
    "itemtotal": 25000,
    "category": "샴푸 바",
    "img": "./images/shampoobar/11.jpg",
    "incense": "",
    "desc": ""
  },
  {
    "id": 43,
    "title": "글로리 215g",
    "price": 51000,
    "price2": "51,000",
    "rate": 5.0,
    "quantity": 1,
    "itemtotal": 51000,
    "category": "헤어 컨디셔너",
    "img": "./images/hair_conditioner/01.jpg",
    "incense": "마카다미아 코코넛오일 올리브오일",
    "desc": "신선한 카카오 버터와 공정하게 얻은 올리브 오일의 만남은 뜨거운 열에 지쳐있던 머리카락에 영광을 되돌려굴 거예요."
  },
  {
    "id": 44,
    "title": "글로리 450g",
    "price": 80000,
    "price2": "80,000",
    "rate": 4.0,
    "quantity": 1,
    "itemtotal": 80000,
    "category": "헤어 컨디셔너",
    "img": "./images/hair_conditioner/02.jpg",
    "incense": "마카다미아 코코넛오일 올리브오일",
    "desc": "신선한 카카오 버터와 공정하게 얻은 올리브 오일의 만남은 뜨거운 열에 지쳐있던 머리카락에 영광을 되돌려굴 거예요."
  },
  {
    "id": 45,
    "title": "글로리 95g",
    "price": 28000,
    "price2": "28,000",
    "rate": 4.83,
    "quantity": 1,
    "itemtotal": 28000,
    "category": "헤어 컨디셔너",
    "img": "./images/hair_conditioner/03.jpg",
    "incense": "마카다미아 코코넛오일 올리브오일",
    "desc": "신선한 카카오 버터와 공정하게 얻은 올리브 오일의 만남은 뜨거운 열에 지쳐있던 머리카락에 영광을 되돌려굴 거예요."
  },
  {
    "id": 46,
    "title": "더 골든 캡 65g",
    "price": 20000,
    "price2": "20,000",
    "rate": 4.83,
    "quantity": 1,
    "itemtotal": 20000,
    "category": "헤어 컨디셔너",
    "img": "./images/hair_conditioner/04.jpg",
    "incense": "바닐라 오렌지",
    "desc": "향기로운 바닐라 향기에 스모키한 매력의 몰약을 더했어요."
  },
  {
    "id": 47,
    "title": "루츠 225g",
    "price": 37000,
    "price2": "37,000",
    "rate": 4.87,
    "quantity": 1,
    "itemtotal": 37000,
    "category": "헤어 컨디셔너",
    "img": "./images/hair_conditioner/05.jpg",
    "incense": "",
    "desc": ""
  },
  {
    "id": 48,
    "title": "루츠 450g",
    "price": 67000,
    "price2": "67,000",
    "rate": 4.78,
    "quantity": 1,
    "itemtotal": 67000,
    "category": "헤어 컨디셔너",
    "img": "./images/hair_conditioner/06.jpg",
    "incense": "",
    "desc": ""
  },
  {
    "id": 49,
    "title": "리트레드 100g",
    "price": 24000,
    "price2": "24,000",
    "rate": 5.0,
    "quantity": 1,
    "itemtotal": 24000,
    "category": "헤어 컨디셔너",
    "img": "./images/hair_conditioner/07.jpg",
    "incense": "",
    "desc": ""
  },
  {
    "id": 50,
    "title": "리트레드 245g",
    "price": 44000,
    "price2": "44,000",
    "rate": 4.79,
    "quantity": 1,
    "itemtotal": 44000,
    "category": "헤어 컨디셔너",
    "img": "./images/hair_conditioner/08.jpg",
    "incense": "",
    "desc": ""
  },
  {
    "id": 51,
    "title": "리트레드 460g",
    "price": 73000,
    "price2": "73,000",
    "rate": 4.5,
    "quantity": 1,
    "itemtotal": 73000,
    "category": "헤어 컨디셔너",
    "img": "./images/hair_conditioner/09.jpg",
    "incense": "",
    "desc": ""
  },
  {
    "id": 52,
    "title": "마릴린 225g",
    "price": 35000,
    "price2": "35,000",
    "rate": 4.75,
    "quantity": 1,
    "itemtotal": 35000,
    "category": "헤어 컨디셔너",
    "img": "./images/hair_conditioner/10.jpg",
    "incense": "",
    "desc": ""
  },
  {
    "id": 53,
    "title": "바나나 230g",
    "price": 40000,
    "price2": "40,000",
    "rate": 4.0,
    "quantity": 1,
    "itemtotal": 40000,
    "category": "헤어 컨디셔너",
    "img": "./images/hair_conditioner/11.jpg",
    "incense": "",
    "desc": ""
  },
  {
    "id": 54,
    "title": "바이올렛 크림 100g",
    "price": 24000,
    "price2": "24,000",
    "rate": 4.56,
    "quantity": 1,
    "itemtotal": 24000,
    "category": "헤어 컨디셔너",
    "img": "./images/hair_conditioner/12.jpg",
    "incense": "",
    "desc": ""
  },
  {
    "id": 55,
    "title": "바이올렛 크림 240g",
    "price": 44000,
    "price2": "44,000",
    "rate": 4.84,
    "quantity": 1,
    "itemtotal": 44000,
    "category": "헤어 컨디셔너",
    "img": "./images/hair_conditioner/13.jpg",
    "incense": "",
    "desc": ""
  },
  {
    "id": 56,
    "title": "바이올렛 크림 450g",
    "price": 73000,
    "price2": "73,000",
    "rate": 4.84,
    "quantity": 1,
    "itemtotal": 73000,
    "category": "헤어 컨디셔너",
    "img": "./images/hair_conditioner/14.jpg",
    "incense": "",
    "desc": ""
  },
  {
    "id": 57,
    "title": "발키리 100g",
    "price": 28000,
    "price2": "28,000",
    "rate": 4.5,
    "quantity": 1,
    "itemtotal": 28000,
    "category": "헤어 컨디셔너",
    "img": "./images/hair_conditioner/15.jpg",
    "incense": "",
    "desc": ""
  },
  {
    "id": 58,
    "title": "발키리 225g",
    "price": 51000,
    "price2": "51,000",
    "rate": 4.73,
    "quantity": 1,
    "itemtotal": 51000,
    "category": "헤어 컨디셔너",
    "img": "./images/hair_conditioner/16.jpg",
    "incense": "",
    "desc": ""
  },
  {
    "id": 59,
    "title": "발키리 450g",
    "price": 80000,
    "price2": "80,000",
    "rate": 4.8,
    "quantity": 1,
    "itemtotal": 80000,
    "category": "헤어 컨디셔너",
    "img": "./images/hair_conditioner/17.jpg",
    "incense": "",
    "desc": ""
  },
  {
    "id": 60,
    "title": "베가니스 100g",
    "price": 20000,
    "price2": "20,000",
    "rate": 4.71,
    "quantity": 1,
    "itemtotal": 20000,
    "category": "헤어 컨디셔너",
    "img": "./images/hair_conditioner/18.jpg",
    "incense": "",
    "desc": ""
  },
  {
    "id": 61,
    "title": "베가니스 225g",
    "price": 40000,
    "price2": "40,000",
    "rate": 4.83,
    "quantity": 1,
    "itemtotal": 40000,
    "category": "헤어 컨디셔너",
    "img": "./images/hair_conditioner/19.jpg",
    "incense": "",
    "desc": ""
  },
  {
    "id": 62,
    "title": "베가니스 450g",
    "price": 66000,
    "price2": "66,000",
    "rate": 4.86,
    "quantity": 1,
    "itemtotal": 66000,
    "category": "헤어 컨디셔너",
    "img": "./images/hair_conditioner/20.jpg",
    "incense": "",
    "desc": ""
  },
  {
    "id": 63,
    "title": "빅 65g",
    "price": 20000,
    "price2": "20,000",
    "rate": 4.58,
    "quantity": 1,
    "itemtotal": 20000,
    "category": "헤어 컨디셔너",
    "img": "./images/hair_conditioner/21.jpg",
    "incense": "",
    "desc": ""
  },
  {
    "id": 64,
    "title": "수안 웬 후아 225g",
    "price": 35000,
    "price2": "35,000",
    "rate": 4.75,
    "quantity": 1,
    "itemtotal": 35000,
    "category": "헤어 컨디셔너",
    "img": "./images/hair_conditioner/22.jpg",
    "incense": "",
    "desc": ""
  },
  {
    "id": 65,
    "title": "아메리칸 크림 100g",
    "price": 20000,
    "price2": "20,000",
    "rate": 4.77,
    "quantity": 1,
    "itemtotal": 20000,
    "category": "헤어 컨디셔너",
    "img": "./images/hair_conditioner/23.jpg",
    "incense": "",
    "desc": ""
  },
  {
    "id": 66,
    "title": "아메리칸 크림 240g",
    "price": 40000,
    "price2": "40,000",
    "rate": 4.81,
    "quantity": 1,
    "itemtotal": 40000,
    "category": "헤어 컨디셔너",
    "img": "./images/hair_conditioner/24.jpg",
    "incense": "",
    "desc": ""
  },
  {
    "id": 67,
    "title": "아메리칸 크림 475g",
    "price": 66000,
    "price2": "66,000",
    "rate": 4.81,
    "quantity": 1,
    "itemtotal": 66000,
    "category": "헤어 컨디셔너",
    "img": "./images/hair_conditioner/25.jpg",
    "incense": "",
    "desc": ""
  },
  {
    "id": 68,
    "title": "아메리칸 크림 65g",
    "price": 20000,
    "price2": "20,000",
    "rate": 4.73,
    "quantity": 1,
    "itemtotal": 20000,
    "category": "헤어 컨디셔너",
    "img": "./images/hair_conditioner/26.jpg",
    "incense": "",
    "desc": ""
  },
  {
    "id": 69,
    "title": "아메리칸 크림 950g",
    "price": 99000,
    "price2": "99,000",
    "rate": 4.94,
    "quantity": 1,
    "itemtotal": 99000,
    "category": "헤어 컨디셔너",
    "img": "./images/hair_conditioner/27.jpg",
    "incense": "",
    "desc": ""
  },
  {
    "id": 70,
    "title": "캔디 레인 1000g",
    "price": 117000,
    "price2": "117,000",
    "rate": 4.6,
    "quantity": 1,
    "itemtotal": 117000,
    "category": "헤어 컨디셔너",
    "img": "./images/hair_conditioner/28.jpg",
    "incense": "",
    "desc": ""
  },
  {
    "id": 71,
    "title": "캔디 레인 100g",
    "price": 24000,
    "price2": "24,000",
    "rate": 4.75,
    "quantity": 1,
    "itemtotal": 24000,
    "category": "헤어 컨디셔너",
    "img": "./images/hair_conditioner/29.jpg",
    "incense": "",
    "desc": ""
  },
  {
    "id": 72,
    "title": "캔디 레인 230g",
    "price": 44000,
    "price2": "44,000",
    "rate": 4.74,
    "quantity": 1,
    "itemtotal": 44000,
    "category": "헤어 컨디셔너",
    "img": "./images/hair_conditioner/30.jpg",
    "incense": "",
    "desc": ""
  },
  {
    "id": 73,
    "title": "캔디 레인 450g",
    "price": 73000,
    "price2": "73,000",
    "rate": 4.74,
    "quantity": 1,
    "itemtotal": 73000,
    "category": "헤어 컨디셔너",
    "img": "./images/hair_conditioner/31.jpg",
    "incense": "",
    "desc": ""
  },
  {
    "id": 74,
    "title": "컬 파워 215g",
    "price": 51000,
    "price2": "51,000",
    "rate": 4.93,
    "quantity": 1,
    "itemtotal": 51000,
    "category": "헤어 컨디셔너",
    "img": "./images/hair_conditioner/32.jpg",
    "incense": "",
    "desc": ""
  },
  {
    "id": 75,
    "title": "컬 파워 95g",
    "price": 28000,
    "price2": "28,000",
    "rate": 4.63,
    "quantity": 1,
    "itemtotal": 28000,
    "category": "헤어 컨디셔너",
    "img": "./images/hair_conditioner/33.jpg",
    "incense": "",
    "desc": ""
  },
  {
    "id": 76,
    "title": "파워 215g",
    "price": 51000,
    "price2": "51,000",
    "rate": 5.0,
    "quantity": 1,
    "itemtotal": 51000,
    "category": "헤어 컨디셔너",
    "img": "./images/hair_conditioner/34.jpg",
    "incense": "",
    "desc": ""
  },
  {
    "id": 77,
    "title": "파워 450g",
    "price": 80000,
    "price2": "80,000",
    "rate": 5.0,
    "quantity": 1,
    "itemtotal": 80000,
    "category": "헤어 컨디셔너",
    "img": "./images/hair_conditioner/35.jpg",
    "incense": "",
    "desc": ""
  },
  {
    "id": 78,
    "title": "파워 95g",
    "price": 28000,
    "price2": "28,000",
    "rate": 5.0,
    "quantity": 1,
    "itemtotal": 28000,
    "category": "헤어 컨디셔너",
    "img": "./images/hair_conditioner/36.jpg",
    "incense": "",
    "desc": ""
  },
  {
    "id": 79,
    "title": "해피 해피 조이 조이 100g",
    "price": 30000,
    "price2": "30,000",
    "rate": 4.73,
    "quantity": 1,
    "itemtotal": 30000,
    "category": "헤어 컨디셔너",
    "img": "./images/hair_conditioner/37.jpg",
    "incense": "",
    "desc": ""
  },
  {
    "id": 80,
    "title": "해피 해피 조이 조이 250g",
    "price": 60000,
    "price2": "60,000",
    "rate": 4.74,
    "quantity": 1,
    "itemtotal": 60000,
    "category": "헤어 컨디셔너",
    "img": "./images/hair_conditioner/38.jpg",
    "incense": "",
    "desc": ""
  },
  {
    "id": 81,
    "title": "해피 해피 조이 조이 480g",
    "price": 100000,
    "price2": "100,000",
    "rate": 4.81,
    "quantity": 1,
    "itemtotal": 100000,
    "category": "헤어 컨디셔너",
    "img": "./images/hair_conditioner/39.jpg",
    "incense": "",
    "desc": ""
  },
  {
    "id": 82,
    "title": "해피 해피 조이 조이 965g",
    "price": 167000,
    "price2": "167,000",
    "rate": 5.0,
    "quantity": 1,
    "itemtotal": 167000,
    "category": "헤어 컨디셔너",
    "img": "./images/hair_conditioner/40.jpg",
    "incense": "",
    "desc": ""
  },
  {
    "id": 83,
    "title": "더티 스타일링 크림 100g",
    "price": 23000,
    "price2": "23,000",
    "rate": 4.79,
    "quantity": 1,
    "itemtotal": 23000,
    "category": "스타일링",
    "img": "./images/styling/01.jpg",
    "incense": "",
    "desc": ""
  },
  {
    "id": 84,
    "title": "더티 스타일링 크림 250g",
    "price": 44000,
    "price2": "44,000",
    "rate": 4.4,
    "quantity": 1,
    "itemtotal": 44000,
    "category": "스타일링",
    "img": "./images/styling/02.jpg",
    "incense": "",
    "desc": ""
  },
  {
    "id": 85,
    "title": "르네스 시어 수플레 190g",
    "price": 59000,
    "price2": "59,000",
    "rate": 5.0,
    "quantity": 1,
    "itemtotal": 59000,
    "category": "스타일링",
    "img": "./images/styling/03.jpg",
    "incense": "",
    "desc": ""
  },
  {
    "id": 86,
    "title": "르네스 시어 수플레 90g",
    "price": 33000,
    "price2": "33,000",
    "rate": 4.82,
    "quantity": 1,
    "itemtotal": 33000,
    "category": "스타일링",
    "img": "./images/styling/04.jpg",
    "incense": "",
    "desc": ""
  },
  {
    "id": 87,
    "title": "밸런스 100g",
    "price": 35000,
    "price2": "35,000",
    "rate": 4.8,
    "quantity": 1,
    "itemtotal": 35000,
    "category": "스타일링",
    "img": "./images/styling/05.jpg",
    "incense": "",
    "desc": ""
  },
  {
    "id": 88,
    "title": "밸런스 225g",
    "price": 65000,
    "price2": "65,000",
    "rate": 4.82,
    "quantity": 1,
    "itemtotal": 65000,
    "category": "스타일링",
    "img": "./images/styling/06.jpg",
    "incense": "",
    "desc": ""
  },
  {
    "id": 89,
    "title": "밸런스 450g",
    "price": 118000,
    "price2": "118,000",
    "rate": 4.0,
    "quantity": 1,
    "itemtotal": 118000,
    "category": "스타일링",
    "img": "./images/styling/07.jpg",
    "incense": "",
    "desc": ""
  },
  {
    "id": 90,
    "title": "수퍼 밀크 100g",
    "price": 38000,
    "price2": "38,000",
    "rate": 4.84,
    "quantity": 1,
    "itemtotal": 38000,
    "category": "스타일링",
    "img": "./images/styling/08.jpg",
    "incense": "",
    "desc": ""
  },
  {
    "id": 91,
    "title": "수퍼 밀크 250g",
    "price": 68000,
    "price2": "68,000",
    "rate": 4.95,
    "quantity": 1,
    "itemtotal": 68000,
    "category": "스타일링",
    "img": "./images/styling/09.jpg",
    "incense": "",
    "desc": ""
  },
  {
    "id": 92,
    "title": "씨 스프레이 100g",
    "price": 33000,
    "price2": "33,000",
    "rate": 4.58,
    "quantity": 1,
    "itemtotal": 33000,
    "category": "스타일링",
    "img": "./images/styling/10.jpg",
    "incense": "",
    "desc": ""
  },
  {
    "id": 93,
    "title": "인프라 위그 100g",
    "price": 22000,
    "price2": "22,000",
    "rate": 4.41,
    "quantity": 1,
    "itemtotal": 22000,
    "category": "스타일링",
    "img": "./images/styling/11.jpg",
    "incense": "",
    "desc": ""
  },
  {
    "id": 94,
    "title": "컬 파워 215g",
    "price": 51000,
    "price2": "51,000",
    "rate": 4.93,
    "quantity": 1,
    "itemtotal": 51000,
    "category": "스타일링",
    "img": "./images/styling/12.jpg",
    "incense": "",
    "desc": ""
  },
  {
    "id": 95,
    "title": "컬 파워 450g",
    "price": 80000,
    "price2": "80,000",
    "rate": 0.0,
    "quantity": 1,
    "itemtotal": 80000,
    "category": "스타일링",
    "img": "./images/styling/13.jpg",
    "incense": "",
    "desc": ""
  },
  {
    "id": 96,
    "title": "컬 파워 95g",
    "price": 28000,
    "price2": "28,000",
    "rate": 4.63,
    "quantity": 1,
    "itemtotal": 28000,
    "category": "스타일링",
    "img": "./images/styling/14.jpg",
    "incense": "",
    "desc": ""
  }
]